sportsdataverse/__init__.py
sportsdataverse/config.py
sportsdataverse/decorators.py
sportsdataverse/dl_utils.py
sportsdataverse/errors.py
sportsdataverse/cfb/__init__.py
sportsdataverse/cfb/cfb_game_rosters.py
sportsdataverse/cfb/cfb_loaders.py
sportsdataverse/cfb/cfb_pbp.py
sportsdataverse/cfb/cfb_schedule.py
sportsdataverse/cfb/cfb_teams.py
sportsdataverse/cfb/model_vars.py
sportsdataverse/cfb/models/ep_model.model
sportsdataverse/cfb/models/qbr_model.model
sportsdataverse/cfb/models/wp_spread.model
sportsdataverse/mbb/__init__.py
sportsdataverse/mbb/mbb_game_rosters.py
sportsdataverse/mbb/mbb_loaders.py
sportsdataverse/mbb/mbb_pbp.py
sportsdataverse/mbb/mbb_schedule.py
sportsdataverse/mbb/mbb_teams.py
sportsdataverse/nba/__init__.py
sportsdataverse/nba/nba_game_rosters.py
sportsdataverse/nba/nba_loaders.py
sportsdataverse/nba/nba_pbp.py
sportsdataverse/nba/nba_schedule.py
sportsdataverse/nba/nba_teams.py
sportsdataverse/nfl/__init__.py
sportsdataverse/nfl/model_vars.py
sportsdataverse/nfl/nfl_game_rosters.py
sportsdataverse/nfl/nfl_games.py
sportsdataverse/nfl/nfl_loaders.py
sportsdataverse/nfl/nfl_pbp.py
sportsdataverse/nfl/nfl_schedule.py
sportsdataverse/nfl/nfl_teams.py
sportsdataverse/nfl/models/ep_model.model
sportsdataverse/nfl/models/qbr_model.model
sportsdataverse/nfl/models/wp_spread.model
sportsdataverse/nhl/__init__.py
sportsdataverse/nhl/nhl_api.py
sportsdataverse/nhl/nhl_game_rosters.py
sportsdataverse/nhl/nhl_loaders.py
sportsdataverse/nhl/nhl_pbp.py
sportsdataverse/nhl/nhl_schedule.py
sportsdataverse/nhl/nhl_teams.py
sportsdataverse/wbb/__init__.py
sportsdataverse/wbb/wbb_game_rosters.py
sportsdataverse/wbb/wbb_loaders.py
sportsdataverse/wbb/wbb_pbp.py
sportsdataverse/wbb/wbb_schedule.py
sportsdataverse/wbb/wbb_teams.py
sportsdataverse/wnba/__init__.py
sportsdataverse/wnba/wnba_game_rosters.py
sportsdataverse/wnba/wnba_loaders.py
sportsdataverse/wnba/wnba_pbp.py
sportsdataverse/wnba/wnba_schedule.py
sportsdataverse/wnba/wnba_teams.py
sportsdataverse-0.0.40.dist-info/licenses/LICENSE
sportsdataverse-0.0.40.dist-info/METADATA
sportsdataverse-0.0.40.dist-info/WHEEL
sportsdataverse-0.0.40.dist-info/top_level.txt
sportsdataverse-0.0.40.dist-info/RECORD
