Metadata-Version: 2.4
Name: sportsdataverse
Version: 0.0.40
Summary: Retrieve Sports data in Python
Home-page: https://github.com/sportsdataverse/sportsdataverse-py
Author: Saiem Gilani
Author-email: saiem.gilani@gmail.com
Maintainer: Saiem Gilani
License: MIT
Project-URL: Docs, https://py.sportsdataverse.org/
Project-URL: Bug Tracker, https://github.com/sportsdataverse/sportsdataverse-py/issues
Keywords: nfl college football data epa statistics web scraping
Classifier: Development Status :: 3 - Alpha
Classifier: Intended Audience :: Developers
Classifier: Topic :: Software Development :: Libraries
Classifier: License :: OSI Approved :: MIT License
Classifier: Programming Language :: Python :: 3
Classifier: Programming Language :: Python :: 3.6
Classifier: Programming Language :: Python :: 3.7
Classifier: Programming Language :: Python :: 3.8
Classifier: Programming Language :: Python :: 3.9
Classifier: Programming Language :: Python :: 3.10
Classifier: Programming Language :: Python :: 3.11
License-File: LICENSE
Requires-Dist: numpy>=1.13.0
Requires-Dist: pandas>=1.0.3
Requires-Dist: polars<=0.18.15
Requires-Dist: tqdm>=4.50.0
Requires-Dist: beautifulsoup4>=4.4.0
Requires-Dist: inflection>=0.5.1
Requires-Dist: requests>=2.18.1
Requires-Dist: lxml>=4.2.1
Requires-Dist: pyarrow>=8.0.0
Requires-Dist: pyjanitor>=0.23.1
Requires-Dist: pyreadr>=0.4.9
Requires-Dist: scipy>=1.4.0
Requires-Dist: matplotlib>=2.0.0
Requires-Dist: attrs>=20.3.0
Requires-Dist: xgboost>=1.2.0
Provides-Extra: tests
Requires-Dist: black>=22.3.0; extra == "tests"
Requires-Dist: flake8>=5.0.0; extra == "tests"
Requires-Dist: isort>=5.10.1; extra == "tests"
Requires-Dist: mypy>=0.782; extra == "tests"
Requires-Dist: pycln>=2.1.6; extra == "tests"
Requires-Dist: pydocstyle>=6.3.0; extra == "tests"
Requires-Dist: pytest>=6.0.2; extra == "tests"
Requires-Dist: pytest-cov>=2.10.1; extra == "tests"
Requires-Dist: pytest-xdist>=2.1.0; extra == "tests"
Provides-Extra: docs
Requires-Dist: sphinx; extra == "docs"
Provides-Extra: models
Requires-Dist: beautifulsoup4>=4.4.0; extra == "models"
Requires-Dist: inflection>=0.5.1; extra == "models"
Requires-Dist: requests>=2.18.1; extra == "models"
Requires-Dist: lxml>=4.2.1; extra == "models"
Requires-Dist: pyarrow>=1.0.1; extra == "models"
Requires-Dist: pyjanitor>=0.23.1; extra == "models"
Requires-Dist: pyreadr>=0.4.0; extra == "models"
Requires-Dist: scipy>=1.4.0; extra == "models"
Requires-Dist: matplotlib>=2.0.0; extra == "models"
Requires-Dist: tqdm>=4.50.0; extra == "models"
Requires-Dist: attrs>=20.3.0; extra == "models"
Requires-Dist: xgboost>=1.2.0; extra == "models"
Provides-Extra: all
Requires-Dist: black>=22.3.0; extra == "all"
Requires-Dist: flake8>=5.0.0; extra == "all"
Requires-Dist: isort>=5.10.1; extra == "all"
Requires-Dist: mypy>=0.782; extra == "all"
Requires-Dist: pycln>=2.1.6; extra == "all"
Requires-Dist: pydocstyle>=6.3.0; extra == "all"
Requires-Dist: pytest>=6.0.2; extra == "all"
Requires-Dist: pytest-cov>=2.10.1; extra == "all"
Requires-Dist: pytest-xdist>=2.1.0; extra == "all"
Requires-Dist: sphinx; extra == "all"
Requires-Dist: beautifulsoup4>=4.4.0; extra == "all"
Requires-Dist: inflection>=0.5.1; extra == "all"
Requires-Dist: requests>=2.18.1; extra == "all"
Requires-Dist: lxml>=4.2.1; extra == "all"
Requires-Dist: pyarrow>=1.0.1; extra == "all"
Requires-Dist: pyjanitor>=0.23.1; extra == "all"
Requires-Dist: pyreadr>=0.4.0; extra == "all"
Requires-Dist: scipy>=1.4.0; extra == "all"
Requires-Dist: matplotlib>=2.0.0; extra == "all"
Requires-Dist: tqdm>=4.50.0; extra == "all"
Requires-Dist: attrs>=20.3.0; extra == "all"
Requires-Dist: xgboost>=1.2.0; extra == "all"
Dynamic: author
Dynamic: author-email
Dynamic: classifier
Dynamic: description
Dynamic: description-content-type
Dynamic: home-page
Dynamic: keywords
Dynamic: license
Dynamic: license-file
Dynamic: maintainer
Dynamic: project-url
Dynamic: provides-extra
Dynamic: requires-dist
Dynamic: summary
